simflow/__init__.py
simflow/iterators.py
simflow/losses.py
simflow/model.py
simflow/optimizers.py
simflow/layers/__init__.py
simflow/layers/activations.py
simflow/layers/convolutional.py
simflow/layers/layer_class.py
simflow/layers/layers.py
simflow/utils/__init__.py
simflow/utils/data_loader_mnist.py
simflow/utils/grad_check_utils.py
simflow/utils/im2col.py
simflow-0.0.1.dist-info/LICENSE
simflow-0.0.1.dist-info/METADATA
simflow-0.0.1.dist-info/WHEEL
simflow-0.0.1.dist-info/top_level.txt
simflow-0.0.1.dist-info/RECORD
