Metadata-Version: 2.1
Name: simflow
Version: 0.0.1
Summary: simflow
Home-page: https://github.com/00arun00/SimFlow
Author: Arun Joseph
Author-email: arunjoseph.eng@gmail.com
License: UNKNOWN
Platform: UNKNOWN
Classifier: Development Status :: 1 - Planning
Classifier: Intended Audience :: Science/Research
Classifier: License :: OSI Approved :: MIT License
Classifier: Programming Language :: Python :: 3
Classifier: Programming Language :: Python :: 3.6
Classifier: Programming Language :: Python :: 3.7
Classifier: Programming Language :: Python :: 3.8
Classifier: Operating System :: OS Independent
